{
  "id": "0346088a-d4b2-4478-aa32-f18e295ec1d9",
  "name": "azure-rediscache",
  "description": "Azure Redis Cache Service",
  "bindable": true,
  "metadata": {
    "displayName": "Azure Redis Cache",
    "imageUrl": "https://cloudfoundry.blob.core.windows.net/assets/RedisCache.png",
    "longDescription": "Azure Redis Cache is based on the popular open-source Redis cache. It gives you access to a secure, dedicated Redis cache, managed by Microsoft and accessible from any application within Azure.",
    "providerDisplayName": "Microsoft"
  },
  "plans": [{
    "id": "362b3d1b-5b57-4289-80ad-4a15a760c29c",
    "name": "basic",
    "free":false,
    "description": "Low network bandwidth, shared infrastructure, up to 256 connections, SSL.",
    "metadata": {
      "bullets": [
        "Low network bandwidth",
        "Shared infrastructure",
        "SSL",
        "Up to 256 connections"
      ],
      "costs": [{
        "amount": {
          "usd": 16.37
        },
        "unit": "monthly estimate"
      }],
      "displayName": "Basic"
    }
  }, {
    "id": "4af8bbd1-962d-4e26-84f1-f72d1d959d87",
    "name": "standard",
    "free":false,
    "description": "Low network bandwidth, dedicated infrastructure, up to 1000 connections, redis config, SSL.",
    "metadata": {
      "bullets": [
        "Low network bandwidth",
        "Dedicated service",
        "SSL",
        "Up to 1000 connections",
        "Configure Redis (key space notifications, etc)",
        "99.9% SLA"
      ],
      "costs": [{
        "amount": {
          "usd": 102.67
        },
        "unit": "monthly estimate"
      }],
      "displayName": "Standard"
    }
  }, {
    "id": "b1057a8f-9a01-423a-bc35-e168d5c04cf0",
    "name": "premium",
    "free":false,
    "description": "Moderate network bandwidth, all standard features, data persistence, virtual network, redis cluster, SSL.",
    "metadata": {
      "bullets": [
        "Moderate network bandwidth",
        "All Standard features",
        "Data Persistence",
        "Virtual Network",
        "Redis cluster",
        "99.9% SLA"
      ],
      "costs": [{
        "amount": {
          "usd": 412.92
        },
        "unit": "monthly estimate per shard"
      }],
      "displayName": "Premium"
    }
  }]
}
